{
  "4f8d7ba675b84644134af34ebc3cee25": {
    "source": "reddit",
    "coin": "bitcoin",
    "start_date": "2025-07-31T20:22:37",
    "end_date": "2025-08-07T20:22:37",
    "num_posts": 200
  },
  "6c59bda3802a0b56f50d1ced0671f43b": {
    "source": "reddit",
    "coin": "bitcoin",
    "analyzer": "VADER",
    "start_date": "2025-07-31T20:35:44",
    "end_date": "2025-08-07T20:35:44",
    "num_posts": 300
  },
  "3f74f1aa855f11aa37103da1536fdadf": {
    "source": "reddit",
    "coin": "bitcoin",
    "analyzer": "VADER",
    "start_date": "2025-07-31T20:41:40",
    "end_date": "2025-08-07T20:41:40",
    "num_posts": 300
  },
  "de09a4f9a04b2d67c4068caaac758a63": {
    "path": "C:\\Users\\PC\\crypto-tracker\\data\\cache\\de09a4f9a04b2d67c4068caaac758a63.csv",
    "rows": 85,
    "updated": 1754652062,
    "settings": {
      "task": "fetch_reddit",
      "source": "reddit",
      "coin": "bitcoin",
      "analyzer": "VADER",
      "start_date": "2025-08-01T11:20:57",
      "end_date": "2025-08-08T11:20:57",
      "num_posts": 300
    }
  },
  "4f14b8581816945823c15ba9f11640a8": {
    "path": "C:\\Users\\PC\\crypto-tracker\\data\\cache\\4f14b8581816945823c15ba9f11640a8.csv",
    "rows": 4,
    "updated": 1754652062,
    "settings": {
      "task": "sentiment_news",
      "source": "news",
      "coin": "bitcoin",
      "analyzer": "VADER",
      "num_posts": 300
    }
  },
  "ac509c15ecc996ae934632314ae740ce": {
    "path": "C:\\Users\\PC\\crypto-tracker\\data\\cache\\ac509c15ecc996ae934632314ae740ce.csv",
    "rows": 85,
    "updated": 1754652064,
    "settings": {
      "task": "sentiment_reddit",
      "source": "reddit",
      "coin": "bitcoin",
      "analyzer": "VADER",
      "num_posts": 300
    }
  },
  "0049f9e498faf4700a000dd74043161c": {
    "path": "C:\\Users\\PC\\crypto-tracker\\data\\cache\\0049f9e498faf4700a000dd74043161c.csv",
    "rows": 169,
    "updated": 1754652065,
    "settings": {
      "task": "fetch_price",
      "coin": "bitcoin",
      "days": "7"
    }
  },
  "a330ff16efc4f83e91a4fa46217de18a": {
    "path": "C:\\Users\\PC\\crypto-tracker\\data\\cache\\a330ff16efc4f83e91a4fa46217de18a.csv",
    "rows": 89,
    "updated": 1754652065,
    "settings": {
      "task": "merge_sentiment_price",
      "coin": "bitcoin",
      "days": "7",
      "analyzer": "VADER",
      "posts_choice": "All"
    }
  },
  "1a3a46fb8254a672ac29f1673ed7b9a7": {
    "path": "C:\\Users\\PC\\crypto-tracker\\data\\cache\\1a3a46fb8254a672ac29f1673ed7b9a7.csv",
    "rows": 85,
    "updated": 1754652085,
    "settings": {
      "task": "fetch_reddit",
      "source": "reddit",
      "coin": "bitcoin",
      "analyzer": "VADER",
      "start_date": "2025-08-01T11:21:22",
      "end_date": "2025-08-08T11:21:22",
      "num_posts": 300
    }
  },
  "001ad33b4aa8e70172c1d97cd2a477ea": {
    "path": "C:\\Users\\PC\\crypto-tracker\\data\\cache\\001ad33b4aa8e70172c1d97cd2a477ea.csv",
    "rows": 85,
    "updated": 1754652191,
    "settings": {
      "task": "fetch_reddit",
      "source": "reddit",
      "coin": "bitcoin",
      "analyzer": "Twitter-RoBERTa",
      "start_date": "2025-08-01T11:23:08",
      "end_date": "2025-08-08T11:23:08",
      "num_posts": 400
    }
  },
  "c60bb16ebc7776d95fba747597398c7c": {
    "path": "C:\\Users\\PC\\crypto-tracker\\data\\cache\\c60bb16ebc7776d95fba747597398c7c.csv",
    "rows": 4,
    "updated": 1754656502,
    "settings": {
      "task": "sentiment_news",
      "source": "news",
      "coin": "bitcoin",
      "analyzer": "Twitter-RoBERTa",
      "num_posts": 400
    }
  },
  "93c16c911d6382a4f2750e912810a42c": {
    "path": "C:\\Users\\PC\\crypto-tracker\\data\\cache\\93c16c911d6382a4f2750e912810a42c.csv",
    "rows": 250,
    "updated": 1754656627,
    "settings": {
      "task": "sentiment_reddit",
      "source": "reddit",
      "coin": "bitcoin",
      "analyzer": "Twitter-RoBERTa",
      "num_posts": 400
    }
  },
  "ac358667bf03188e9d4102ef620116e6": {
    "path": "C:\\Users\\PC\\crypto-tracker\\data\\cache\\ac358667bf03188e9d4102ef620116e6.csv",
    "rows": 89,
    "updated": 1754652243,
    "settings": {
      "task": "merge_sentiment_price",
      "coin": "bitcoin",
      "days": "7",
      "analyzer": "Twitter-RoBERTa",
      "posts_choice": "All"
    }
  },
  "d38cea34b5fab53769af79c41017e582": {
    "path": "C:\\Users\\PC\\crypto-tracker\\data\\cache\\d38cea34b5fab53769af79c41017e582.csv",
    "rows": 250,
    "updated": 1754656494,
    "settings": {
      "task": "fetch_reddit",
      "source": "reddit",
      "coin": "bitcoin",
      "analyzer": "Twitter-RoBERTa",
      "start_date": "2025-05-10T12:34:49",
      "end_date": "2025-08-08T12:34:49",
      "num_posts": 400
    }
  },
  "ebb3e1822b41afd6be30be0d6b6d09df": {
    "path": "C:\\Users\\PC\\crypto-tracker\\data\\cache\\ebb3e1822b41afd6be30be0d6b6d09df.csv",
    "rows": 2161,
    "updated": 1754656628,
    "settings": {
      "task": "fetch_price",
      "coin": "bitcoin",
      "days": "90"
    }
  },
  "13f86513e6f34cb2c921a2db7b68d655": {
    "path": "C:\\Users\\PC\\crypto-tracker\\data\\cache\\13f86513e6f34cb2c921a2db7b68d655.csv",
    "rows": 254,
    "updated": 1754656628,
    "settings": {
      "task": "merge_sentiment_price",
      "coin": "bitcoin",
      "days": "90",
      "analyzer": "Twitter-RoBERTa",
      "posts_choice": "All"
    }
  },
  "3fefc47ea53e8e3a7e8f6491e31287f2": {
    "path": "C:\\Users\\PC\\crypto-tracker\\data\\cache\\3fefc47ea53e8e3a7e8f6491e31287f2.csv",
    "rows": 250,
    "updated": 1754657801,
    "settings": {
      "task": "fetch_reddit",
      "source": "reddit",
      "coin": "bitcoin",
      "analyzer": "Twitter-RoBERTa",
      "start_date": "2025-05-10T12:56:37",
      "end_date": "2025-08-08T12:56:37",
      "num_posts": 400
    }
  },
  "748222060f92c04d76bf9c3856235121": {
    "path": "C:\\Users\\PC\\crypto-tracker\\data\\cache\\748222060f92c04d76bf9c3856235121.csv",
    "rows": 250,
    "updated": 1754657831,
    "settings": {
      "task": "fetch_reddit",
      "source": "reddit",
      "coin": "bitcoin",
      "analyzer": "Twitter-RoBERTa",
      "start_date": "2025-05-10T12:57:08",
      "end_date": "2025-08-08T12:57:08",
      "num_posts": 300
    }
  },
  "5ccc371ff7f23509dc71dcbad702b958": {
    "path": "C:\\Users\\PC\\crypto-tracker\\data\\cache\\5ccc371ff7f23509dc71dcbad702b958.csv",
    "rows": 4,
    "updated": 1754657833,
    "settings": {
      "task": "sentiment_news",
      "source": "news",
      "coin": "bitcoin",
      "analyzer": "Twitter-RoBERTa",
      "num_posts": 300
    }
  },
  "028195fe91b0a31c8decfe9d48f7155f": {
    "path": "C:\\Users\\PC\\crypto-tracker\\data\\cache\\028195fe91b0a31c8decfe9d48f7155f.csv",
    "rows": 250,
    "updated": 1754658021,
    "settings": {
      "task": "sentiment_reddit",
      "source": "reddit",
      "coin": "bitcoin",
      "analyzer": "Twitter-RoBERTa",
      "num_posts": 300
    }
  },
  "79b200fb0014061153eb83687b45b46d": {
    "path": "D:\\Projects\\Crypto-tracker\\Crypto-sentiment-tracker\\data\\cache\\79b200fb0014061153eb83687b45b46d.csv",
    "rows": 4,
    "updated": 1754771935,
    "settings": {
      "coin": "bitcoin",
      "dataset": "posts",
      "end_date": "2025-08-09T20:38:54",
      "num_posts": 300,
      "query": "btc",
      "source": "news",
      "start_date": "2025-08-02T20:38:54"
    }
  },
  "c830ff2dde1ec2710c07228b7167391c": {
    "path": "D:\\Projects\\Crypto-tracker\\Crypto-sentiment-tracker\\data\\cache\\c830ff2dde1ec2710c07228b7167391c.csv",
    "rows": 84,
    "updated": 1754771939,
    "settings": {
      "coin": "bitcoin",
      "dataset": "posts",
      "end_date": "2025-08-09T20:38:54",
      "num_posts": 300,
      "query": "bitcoin",
      "source": "reddit",
      "start_date": "2025-08-02T20:38:54"
    }
  },
  "65bd0936c300d8e96ed57808aa9246f2": {
    "path": "D:\\Projects\\Crypto-tracker\\Crypto-sentiment-tracker\\data\\cache\\65bd0936c300d8e96ed57808aa9246f2.csv",
    "rows": 4,
    "updated": 1754771939,
    "settings": {
      "analyzer": "vader",
      "coin": "bitcoin",
      "dataset": "sentiment",
      "input_sha1": "fe14c6547ed4993020253c04e2a8e8f434021ce8",
      "source": "news"
    }
  },
  "a0bde3f0db1cecea3c2db72497862e51": {
    "path": "D:\\Projects\\Crypto-tracker\\Crypto-sentiment-tracker\\data\\cache\\a0bde3f0db1cecea3c2db72497862e51.csv",
    "rows": 84,
    "updated": 1754771940,
    "settings": {
      "analyzer": "vader",
      "coin": "bitcoin",
      "dataset": "sentiment",
      "input_sha1": "4ae5c8f78d74b153c8da7901c11a325d929d27c9",
      "source": "reddit"
    }
  },
  "0a2b0f4e46d6fc6c16b077317f022599": {
    "path": "D:\\Projects\\Crypto-tracker\\Crypto-sentiment-tracker\\data\\cache\\0a2b0f4e46d6fc6c16b077317f022599.csv",
    "rows": 169,
    "updated": 1754788487,
    "settings": {
      "coin": "bitcoin",
      "dataset": "price",
      "days": 7
    }
  },
  "1fc4b553d89d8303a9401a8aa0a3b57e": {
    "path": "D:\\Projects\\Crypto-tracker\\Crypto-sentiment-tracker\\data\\cache\\1fc4b553d89d8303a9401a8aa0a3b57e.csv",
    "rows": 88,
    "updated": 1754771940,
    "settings": {
      "analyzer": "vader",
      "coin": "bitcoin",
      "dataset": "merged",
      "days": 7,
      "depends_on": [
        "648cd392bcbfdc7f55ab34b964affc5b2d9ff16a",
        "887438625090569fa16c11a4ba202b48feb3dabb"
      ],
      "posts_choice": "all"
    }
  },
  "65de460489bd30128d15ccafb752b916": {
    "path": "D:\\Projects\\Crypto-tracker\\Crypto-sentiment-tracker\\data\\cache\\65de460489bd30128d15ccafb752b916.csv",
    "rows": 5,
    "updated": 1754788481,
    "settings": {
      "coin": "bitcoin",
      "dataset": "posts",
      "end_date": "2025-08-10T01:14:41",
      "num_posts": 500,
      "query": "btc",
      "source": "news",
      "start_date": "2025-08-03T01:14:41"
    }
  },
  "3661cc13d8b716416c4cabb684134952": {
    "path": "D:\\Projects\\Crypto-tracker\\Crypto-sentiment-tracker\\data\\cache\\3661cc13d8b716416c4cabb684134952.csv",
    "rows": 82,
    "updated": 1754788485,
    "settings": {
      "coin": "bitcoin",
      "dataset": "posts",
      "end_date": "2025-08-10T01:14:41",
      "num_posts": 500,
      "query": "bitcoin",
      "source": "reddit",
      "start_date": "2025-08-03T01:14:41"
    }
  },
  "0f623b018f01f38ec2bfdfae8020667d": {
    "path": "D:\\Projects\\Crypto-tracker\\Crypto-sentiment-tracker\\data\\cache\\0f623b018f01f38ec2bfdfae8020667d.csv",
    "rows": 5,
    "updated": 1754788486,
    "settings": {
      "analyzer": "vader",
      "coin": "bitcoin",
      "dataset": "sentiment",
      "input_sha1": "dc37d5cce4a0bb5f215a3650a7c8dbeecfce3596",
      "source": "news"
    }
  },
  "ce254a4a00eb89020111c77bb55d71fd": {
    "path": "D:\\Projects\\Crypto-tracker\\Crypto-sentiment-tracker\\data\\cache\\ce254a4a00eb89020111c77bb55d71fd.csv",
    "rows": 82,
    "updated": 1754788486,
    "settings": {
      "analyzer": "vader",
      "coin": "bitcoin",
      "dataset": "sentiment",
      "input_sha1": "1c49025920c9a1b01766e1e191e175113757e03e",
      "source": "reddit"
    }
  },
  "75e759cc2b018216d941ef5ab7f9d583": {
    "path": "D:\\Projects\\Crypto-tracker\\Crypto-sentiment-tracker\\data\\cache\\75e759cc2b018216d941ef5ab7f9d583.csv",
    "rows": 87,
    "updated": 1754788487,
    "settings": {
      "analyzer": "vader",
      "coin": "bitcoin",
      "dataset": "merged",
      "days": 7,
      "depends_on": [
        "3dc662819bdeaefaa2c87700798cc739ff7a24c3",
        "84daf539784ac89d37773f541a05c45b78541f7d"
      ],
      "posts_choice": "all"
    }
  },
  "d2ebe60230ee03bf0e001b2dcd32acdb": {
    "path": "D:\\Projects\\Crypto-tracker\\Crypto-sentiment-tracker\\data\\cache\\d2ebe60230ee03bf0e001b2dcd32acdb.csv",
    "rows": 193,
    "updated": 1754788487,
    "settings": {
      "analyzer": "vader",
      "coin": "bitcoin",
      "dataset": "features",
      "days": 7,
      "depends_on": [
        "3db04530e9c243ad44818a9cda3c41fffe69cdac"
      ],
      "lag_max_s": 86400,
      "lag_min_s": -86400,
      "lag_step_s": 900,
      "metric": "pearson",
      "posts_choice": "all"
    }
  },
  "e3a1e22d5e0f6f4a9638a388a9c11c62": {
    "path": "D:\\Projects\\Crypto-tracker\\Crypto-sentiment-tracker\\data\\cache\\e3a1e22d5e0f6f4a9638a388a9c11c62.csv",
    "rows": 5,
    "updated": 1754788541,
    "settings": {
      "coin": "bitcoin",
      "dataset": "posts",
      "end_date": "2025-08-10T01:15:40",
      "num_posts": 600,
      "query": "btc",
      "source": "news",
      "start_date": "2025-08-03T01:15:40"
    }
  },
  "d17da8fab766f2a52ef2a5d112df08b6": {
    "path": "D:\\Projects\\Crypto-tracker\\Crypto-sentiment-tracker\\data\\cache\\d17da8fab766f2a52ef2a5d112df08b6.csv",
    "rows": 82,
    "updated": 1754788544,
    "settings": {
      "coin": "bitcoin",
      "dataset": "posts",
      "end_date": "2025-08-10T01:15:40",
      "num_posts": 600,
      "query": "bitcoin",
      "source": "reddit",
      "start_date": "2025-08-03T01:15:40"
    }
  },
  "7cb99636b253dc556b7af0e514c70de3": {
    "path": "D:\\Projects\\Crypto-tracker\\Crypto-sentiment-tracker\\data\\cache\\7cb99636b253dc556b7af0e514c70de3.csv",
    "rows": 5,
    "updated": 1754788608,
    "settings": {
      "coin": "bitcoin",
      "dataset": "posts",
      "end_date": "2025-08-10T01:16:48",
      "num_posts": 600,
      "query": "btc",
      "source": "news",
      "start_date": "2025-07-11T01:16:48"
    }
  },
  "de0b61a05eb3c01028e3ae89c7864333": {
    "path": "D:\\Projects\\Crypto-tracker\\Crypto-sentiment-tracker\\data\\cache\\de0b61a05eb3c01028e3ae89c7864333.csv",
    "rows": 250,
    "updated": 1754788612,
    "settings": {
      "coin": "bitcoin",
      "dataset": "posts",
      "end_date": "2025-08-10T01:16:48",
      "num_posts": 600,
      "query": "bitcoin",
      "source": "reddit",
      "start_date": "2025-07-11T01:16:48"
    }
  },
  "63d1404e81b6cd94c5fcad3334420a56": {
    "path": "D:\\Projects\\Crypto-tracker\\Crypto-sentiment-tracker\\data\\cache\\63d1404e81b6cd94c5fcad3334420a56.csv",
    "rows": 250,
    "updated": 1754788615,
    "settings": {
      "analyzer": "vader",
      "coin": "bitcoin",
      "dataset": "sentiment",
      "input_sha1": "737e67db2d558a7b53f87ff6c1700532791edd48",
      "source": "reddit"
    }
  },
  "54658b7381788874b7c464225255fae9": {
    "path": "D:\\Projects\\Crypto-tracker\\Crypto-sentiment-tracker\\data\\cache\\54658b7381788874b7c464225255fae9.csv",
    "rows": 721,
    "updated": 1754822921,
    "settings": {
      "coin": "bitcoin",
      "dataset": "price",
      "days": 30
    }
  },
  "00bfaceefb9788652cbdaa3e2ec662a9": {
    "path": "D:\\Projects\\Crypto-tracker\\Crypto-sentiment-tracker\\data\\cache\\00bfaceefb9788652cbdaa3e2ec662a9.csv",
    "rows": 255,
    "updated": 1754788615,
    "settings": {
      "analyzer": "vader",
      "coin": "bitcoin",
      "dataset": "merged",
      "days": 30,
      "depends_on": [
        "1ec686d6697cf86bdfd0e923739d5fcfdfed1a74",
        "583171388eb02d2114ac61fd6348839752b84ed2"
      ],
      "posts_choice": "all"
    }
  },
  "27bca1d50eb7b0f8620f2bb84557d419": {
    "path": "D:\\Projects\\Crypto-tracker\\Crypto-sentiment-tracker\\data\\cache\\27bca1d50eb7b0f8620f2bb84557d419.csv",
    "rows": 193,
    "updated": 1754788615,
    "settings": {
      "analyzer": "vader",
      "coin": "bitcoin",
      "dataset": "features",
      "days": 30,
      "depends_on": [
        "8cb0b808d6180d20436b2da1959d40b4b4a61b2d"
      ],
      "lag_max_s": 86400,
      "lag_min_s": -86400,
      "lag_step_s": 900,
      "metric": "pearson",
      "posts_choice": "all"
    }
  },
  "d6b68343be8695609afc1d53a0b8b91c": {
    "path": "D:\\Projects\\Crypto-tracker\\Crypto-sentiment-tracker\\data\\cache\\d6b68343be8695609afc1d53a0b8b91c.csv",
    "rows": 5,
    "updated": 1754788670,
    "settings": {
      "coin": "bitcoin",
      "dataset": "posts",
      "end_date": "2025-08-10T01:17:50",
      "num_posts": 1000,
      "query": "btc",
      "source": "news",
      "start_date": "2025-05-12T01:17:50"
    }
  },
  "295679f449cd0579a3e06c3a2be5def4": {
    "path": "D:\\Projects\\Crypto-tracker\\Crypto-sentiment-tracker\\data\\cache\\295679f449cd0579a3e06c3a2be5def4.csv",
    "rows": 250,
    "updated": 1754788674,
    "settings": {
      "coin": "bitcoin",
      "dataset": "posts",
      "end_date": "2025-08-10T01:17:50",
      "num_posts": 1000,
      "query": "bitcoin",
      "source": "reddit",
      "start_date": "2025-05-12T01:17:50"
    }
  },
  "a36cf7db5755bdf165899606efdd3a97": {
    "path": "D:\\Projects\\Crypto-tracker\\Crypto-sentiment-tracker\\data\\cache\\a36cf7db5755bdf165899606efdd3a97.csv",
    "rows": 2161,
    "updated": 1754824341,
    "settings": {
      "coin": "bitcoin",
      "dataset": "price",
      "days": 90
    }
  },
  "9261973a22365ad87579c003650c344c": {
    "path": "D:\\Projects\\Crypto-tracker\\Crypto-sentiment-tracker\\data\\cache\\9261973a22365ad87579c003650c344c.csv",
    "rows": 255,
    "updated": 1754788674,
    "settings": {
      "analyzer": "vader",
      "coin": "bitcoin",
      "dataset": "merged",
      "days": 90,
      "depends_on": [
        "06a662e25f18bdffa8a2604f4f09f7fb3ab51e57",
        "1ec686d6697cf86bdfd0e923739d5fcfdfed1a74"
      ],
      "posts_choice": "all"
    }
  },
  "3668033c9f1d3e45792887eec1b37600": {
    "path": "D:\\Projects\\Crypto-tracker\\Crypto-sentiment-tracker\\data\\cache\\3668033c9f1d3e45792887eec1b37600.csv",
    "rows": 193,
    "updated": 1754788675,
    "settings": {
      "analyzer": "vader",
      "coin": "bitcoin",
      "dataset": "features",
      "days": 90,
      "depends_on": [
        "8cb0b808d6180d20436b2da1959d40b4b4a61b2d"
      ],
      "lag_max_s": 86400,
      "lag_min_s": -86400,
      "lag_step_s": 900,
      "metric": "pearson",
      "posts_choice": "all"
    }
  },
  "4feda211be61e8fc57c7bc22bf213092": {
    "path": "D:\\Projects\\Crypto-tracker\\Crypto-sentiment-tracker\\data\\cache\\4feda211be61e8fc57c7bc22bf213092.csv",
    "rows": 5,
    "updated": 1754788699,
    "settings": {
      "coin": "bitcoin",
      "dataset": "posts",
      "end_date": "2025-08-10T01:18:18",
      "num_posts": 800,
      "query": "btc",
      "source": "news",
      "start_date": "2025-05-12T01:18:18"
    }
  },
  "93197e4fcc497d574d9947876a28e9af": {
    "path": "D:\\Projects\\Crypto-tracker\\Crypto-sentiment-tracker\\data\\cache\\93197e4fcc497d574d9947876a28e9af.csv",
    "rows": 250,
    "updated": 1754788702,
    "settings": {
      "coin": "bitcoin",
      "dataset": "posts",
      "end_date": "2025-08-10T01:18:18",
      "num_posts": 800,
      "query": "bitcoin",
      "source": "reddit",
      "start_date": "2025-05-12T01:18:18"
    }
  },
  "e127a9df783ea566bf1f0f3de1341869": {
    "path": "D:\\Projects\\Crypto-tracker\\Crypto-sentiment-tracker\\data\\cache\\e127a9df783ea566bf1f0f3de1341869.csv",
    "rows": 5,
    "updated": 1754788712,
    "settings": {
      "coin": "bitcoin",
      "dataset": "posts",
      "end_date": "2025-08-10T01:18:32",
      "num_posts": 800,
      "query": "btc",
      "source": "news",
      "start_date": "2025-05-12T01:18:32"
    }
  },
  "6acd2197a44ab2b6dcec1e6549cd7d05": {
    "path": "D:\\Projects\\Crypto-tracker\\Crypto-sentiment-tracker\\data\\cache\\6acd2197a44ab2b6dcec1e6549cd7d05.csv",
    "rows": 250,
    "updated": 1754788715,
    "settings": {
      "coin": "bitcoin",
      "dataset": "posts",
      "end_date": "2025-08-10T01:18:32",
      "num_posts": 800,
      "query": "bitcoin",
      "source": "reddit",
      "start_date": "2025-05-12T01:18:32"
    }
  },
  "dcc316243a61b2c4b6bf6488b513f82f": {
    "path": "D:\\Projects\\Crypto-tracker\\Crypto-sentiment-tracker\\data\\cache\\dcc316243a61b2c4b6bf6488b513f82f.csv",
    "rows": 385,
    "updated": 1754788716,
    "settings": {
      "analyzer": "vader",
      "coin": "bitcoin",
      "dataset": "features",
      "days": 90,
      "depends_on": [
        "8cb0b808d6180d20436b2da1959d40b4b4a61b2d"
      ],
      "lag_max_s": 172800,
      "lag_min_s": -172800,
      "lag_step_s": 900,
      "metric": "pearson",
      "posts_choice": "all"
    }
  },
  "713b00419d9747b78861cd8c971d5d4c": {
    "path": "D:\\Projects\\Crypto-tracker\\Crypto-sentiment-tracker\\data\\cache\\713b00419d9747b78861cd8c971d5d4c.csv",
    "rows": 6,
    "updated": 1754822914,
    "settings": {
      "coin": "bitcoin",
      "dataset": "posts",
      "end_date": "2025-08-10T10:48:34",
      "num_posts": 500,
      "query": "btc",
      "source": "news",
      "start_date": "2025-07-11T10:48:34"
    }
  },
  "0001aade56cf7d8f2ba34fdb7e6ef973": {
    "path": "D:\\Projects\\Crypto-tracker\\Crypto-sentiment-tracker\\data\\cache\\0001aade56cf7d8f2ba34fdb7e6ef973.csv",
    "rows": 250,
    "updated": 1754822918,
    "settings": {
      "coin": "bitcoin",
      "dataset": "posts",
      "end_date": "2025-08-10T10:48:34",
      "num_posts": 500,
      "query": "bitcoin",
      "source": "reddit",
      "start_date": "2025-07-11T10:48:34"
    }
  },
  "f59f7489cbcea165bf9797ab233723cc": {
    "path": "D:\\Projects\\Crypto-tracker\\Crypto-sentiment-tracker\\data\\cache\\f59f7489cbcea165bf9797ab233723cc.csv",
    "rows": 6,
    "updated": 1754822918,
    "settings": {
      "analyzer": "vader",
      "coin": "bitcoin",
      "dataset": "sentiment",
      "input_sha1": "d30e70708f9eb093a6eb34924de0a3682164f0e7",
      "source": "news"
    }
  },
  "3f96e65828449582b3f59cadfb9bedb7": {
    "path": "D:\\Projects\\Crypto-tracker\\Crypto-sentiment-tracker\\data\\cache\\3f96e65828449582b3f59cadfb9bedb7.csv",
    "rows": 250,
    "updated": 1754822920,
    "settings": {
      "analyzer": "vader",
      "coin": "bitcoin",
      "dataset": "sentiment",
      "input_sha1": "990317c8f410c9677adcb17b808bc2442d0c9974",
      "source": "reddit"
    }
  },
  "5b6965d43e90e865adfc8ae7280011d1": {
    "path": "D:\\Projects\\Crypto-tracker\\Crypto-sentiment-tracker\\data\\cache\\5b6965d43e90e865adfc8ae7280011d1.csv",
    "rows": 256,
    "updated": 1754822921,
    "settings": {
      "analyzer": "vader",
      "coin": "bitcoin",
      "dataset": "merged",
      "days": 30,
      "depends_on": [
        "a8506f2fc43eef04268e2a68f0431f84bc09506f",
        "d0bc9aacc2ac1f183c074992ad00023d88279162"
      ],
      "posts_choice": "all"
    }
  },
  "06292d89d4be5d9bf6d8afd3ae17ea1d": {
    "path": "D:\\Projects\\Crypto-tracker\\Crypto-sentiment-tracker\\data\\cache\\06292d89d4be5d9bf6d8afd3ae17ea1d.csv",
    "rows": 193,
    "updated": 1754822921,
    "settings": {
      "analyzer": "vader",
      "coin": "bitcoin",
      "dataset": "features",
      "days": 30,
      "depends_on": [
        "2879cc545923b9431bf7f79732e3999470131510"
      ],
      "lag_max_s": 86400,
      "lag_min_s": -86400,
      "lag_step_s": 900,
      "metric": "pearson",
      "posts_choice": "all"
    }
  },
  "7cdf3ef13a601380d7dcd680cd0233c7": {
    "path": "D:\\Projects\\Crypto-tracker\\Crypto-sentiment-tracker\\data\\cache\\7cdf3ef13a601380d7dcd680cd0233c7.csv",
    "rows": 249,
    "updated": 1754824338,
    "settings": {
      "coin": "bitcoin",
      "dataset": "posts",
      "end_date": "2025-08-10T11:12:14",
      "num_posts": 700,
      "query": "(bitcoin or bitcoin)",
      "source": "reddit",
      "start_date": "2025-05-12T11:12:14",
      "subreddits": [
        "bitcoin",
        "bitcoinmarkets",
        "cryptocurrency",
        "cryptocurrencytrading",
        "cryptomarkets"
      ]
    }
  },
  "982df69819397911e16bd02d2b4ee7aa": {
    "path": "D:\\Projects\\Crypto-tracker\\Crypto-sentiment-tracker\\data\\cache\\982df69819397911e16bd02d2b4ee7aa.csv",
    "rows": 249,
    "updated": 1754824340,
    "settings": {
      "analyzer": "vader",
      "coin": "bitcoin",
      "dataset": "sentiment",
      "input_sha1": "e9f3dcd9f858483ce519bbf267462ac2618cef1a",
      "source": "reddit"
    }
  },
  "016579f5df4eeca1f41d8253fc45d933": {
    "path": "D:\\Projects\\Crypto-tracker\\Crypto-sentiment-tracker\\data\\cache\\016579f5df4eeca1f41d8253fc45d933.csv",
    "rows": 249,
    "updated": 1754824341,
    "settings": {
      "analyzer": "vader",
      "coin": "bitcoin",
      "dataset": "merged",
      "days": 90,
      "depends_on": [
        "3238788cf4015cef7a4e0b68d36c70d69a3c3253",
        "663889392c6ecd890535482d5ffe48841fc2e0a5"
      ],
      "posts_choice": "reddit"
    }
  },
  "1404ce180e4aeac1babd9579ebed740d": {
    "path": "D:\\Projects\\Crypto-tracker\\Crypto-sentiment-tracker\\data\\cache\\1404ce180e4aeac1babd9579ebed740d.csv",
    "rows": 193,
    "updated": 1754824341,
    "settings": {
      "analyzer": "vader",
      "coin": "bitcoin",
      "dataset": "features",
      "days": 90,
      "depends_on": [
        "3c13a624f52e16d550f3d763165be8778374e5cd"
      ],
      "lag_max_s": 86400,
      "lag_min_s": -86400,
      "lag_step_s": 900,
      "metric": "pearson",
      "posts_choice": "reddit"
    }
  },
  "dd1e33323e899402c527dd969bef51c7": {
    "path": "D:\\Projects\\Crypto-tracker\\Crypto-sentiment-tracker\\data\\cache\\dd1e33323e899402c527dd969bef51c7.csv",
    "rows": 249,
    "updated": 1754824429,
    "settings": {
      "coin": "bitcoin",
      "dataset": "posts",
      "end_date": "2025-08-10T11:13:46",
      "num_posts": 700,
      "query": "(bitcoin or bitcoin)",
      "source": "reddit",
      "start_date": "2025-07-11T11:13:46",
      "subreddits": [
        "bitcoin",
        "bitcoinmarkets",
        "cryptocurrency",
        "cryptocurrencytrading",
        "cryptomarkets"
      ]
    }
  },
  "4ad954b5d36f8e21cdf4e7c16e0f3cb0": {
    "path": "D:\\Projects\\Crypto-tracker\\Crypto-sentiment-tracker\\data\\cache\\4ad954b5d36f8e21cdf4e7c16e0f3cb0.csv",
    "rows": 249,
    "updated": 1754824432,
    "settings": {
      "analyzer": "vader",
      "coin": "bitcoin",
      "dataset": "sentiment",
      "input_sha1": "3e9fcd3710c263ff0f2a9d9c27c7f9f4f2d51105",
      "source": "reddit"
    }
  },
  "d800269a57f038e786e13397f09866b4": {
    "path": "D:\\Projects\\Crypto-tracker\\Crypto-sentiment-tracker\\data\\cache\\d800269a57f038e786e13397f09866b4.csv",
    "rows": 249,
    "updated": 1754824432,
    "settings": {
      "analyzer": "vader",
      "coin": "bitcoin",
      "dataset": "merged",
      "days": 30,
      "depends_on": [
        "2f43217d3aac1fce37c156c88aae8d6022198800",
        "3238788cf4015cef7a4e0b68d36c70d69a3c3253"
      ],
      "posts_choice": "reddit"
    }
  },
  "e15780be56f6d721873cfe41567f8213": {
    "path": "D:\\Projects\\Crypto-tracker\\Crypto-sentiment-tracker\\data\\cache\\e15780be56f6d721873cfe41567f8213.csv",
    "rows": 193,
    "updated": 1754824432,
    "settings": {
      "analyzer": "vader",
      "coin": "bitcoin",
      "dataset": "features",
      "days": 30,
      "depends_on": [
        "ebed91840a903604f54ae30aa9e69812a2302f08"
      ],
      "lag_max_s": 86400,
      "lag_min_s": -86400,
      "lag_step_s": 900,
      "metric": "pearson",
      "posts_choice": "reddit"
    }
  }
}